README.rst
setup.py
src/mog_commons/__init__.py
src/mog_commons/case_class.py
src/mog_commons/collection.py
src/mog_commons/command.py
src/mog_commons/functional.py
src/mog_commons/io.py
src/mog_commons/string.py
src/mog_commons/terminal.py
src/mog_commons/types.py
src/mog_commons/unittest.py
src/mog_commons.egg-info/PKG-INFO
src/mog_commons.egg-info/SOURCES.txt
src/mog_commons.egg-info/dependency_links.txt
src/mog_commons.egg-info/requires.txt
src/mog_commons.egg-info/top_level.txt
src/mog_commons/backported/__init__.py
src/mog_commons/backported/inspect2.py