Metadata-Version: 1.0
Name: mog-commons
Version: 0.2.2
Summary: Common utility library for Python
Home-page: https://github.com/mogproject/mog-commons-python
Author: mogproject
Author-email: mogproj@gmail.com
License: Apache 2.0 License
Platform: UNKNOWN
